jbpy/__init__.py
jbpy/_jbpdump.py
jbpy/_jbpinfo.py
jbpy/core.py
jbpy/image_data.py
jbpy/py.typed
jbpy/examples/README.md
jbpy/examples/__init__.py
jbpy/examples/extract_nitf_image.py
jbpy/extensions/__init__.py
jbpy/extensions/des_subheader/__init__.py
jbpy/extensions/des_subheader/xml_data_content.py
jbpy/extensions/tre/BLOCKA.py
jbpy/extensions/tre/EXOPTA.py
jbpy/extensions/tre/GEOPSB.py
jbpy/extensions/tre/ICHIPB.py
jbpy/extensions/tre/J2KLRA.py
jbpy/extensions/tre/PRJPSB.py
jbpy/extensions/tre/REGPTB.py
jbpy/extensions/tre/RPC00B.py
jbpy/extensions/tre/SECTGA.py
jbpy/extensions/tre/STDIDC.py
jbpy/extensions/tre/USE00A.py
jbpy/extensions/tre/__init__.py
jbpy/extensions/tre/_core.py
jbpy-0.5.1.dist-info/licenses/LICENSE
jbpy-0.5.1.dist-info/METADATA
jbpy-0.5.1.dist-info/WHEEL
jbpy-0.5.1.dist-info/entry_points.txt
jbpy-0.5.1.dist-info/top_level.txt
jbpy-0.5.1.dist-info/RECORD
