Metadata-Version: 2.4
Name: jbpy
Version: 0.5.1
Summary: Library for reading and writing Joint BIIF Profile (JBP) files (NITF and NSIF)
Author: Valkyrie Systems Corporation
License-Expression: MIT
Project-URL: Repository, https://github.com/ValkyrieSystems/jbpy
Project-URL: Bug Tracker, https://github.com/ValkyrieSystems/jbpy/issues
Project-URL: Changelog, https://github.com/ValkyrieSystems/jbpy/blob/main/CHANGELOG.md
Classifier: Development Status :: 4 - Beta
Classifier: Intended Audience :: Developers
Classifier: Programming Language :: Python :: 3.11
Classifier: Programming Language :: Python :: 3.12
Classifier: Programming Language :: Python :: 3.13
Classifier: Programming Language :: Python :: 3.14
Requires-Python: >=3.11
License-File: LICENSE
Provides-Extra: dev
Requires-Dist: aiohttp; extra == "dev"
Requires-Dist: mypy; extra == "dev"
Requires-Dist: ruff; extra == "dev"
Requires-Dist: pytest; extra == "dev"
Requires-Dist: smart_open[http]; extra == "dev"
Requires-Dist: numpy; extra == "dev"
Requires-Dist: jbpy[examples]; extra == "dev"
Provides-Extra: examples
Requires-Dist: numpy; extra == "examples"
Requires-Dist: pillow; extra == "examples"
Dynamic: license-file
